compas_dr/__init__.py
compas_dr/__main__.py
compas_dr/install.py
compas_dr/numdata.py
compas_dr/types.py
compas_dr/constraints/__init__.py
compas_dr/constraints/circleconstraint.py
compas_dr/constraints/constraint.py
compas_dr/constraints/curveconstraint.py
compas_dr/constraints/exceptions.py
compas_dr/constraints/lineconstraint.py
compas_dr/constraints/planeconstraint.py
compas_dr/constraints/surfaceconstraint.py
compas_dr/loads/__init__.py
compas_dr/loads/selfweight.py
compas_dr/solvers/__init__.py
compas_dr/solvers/dr.py
compas_dr/solvers/dr_constrained_numpy.py
compas_dr/solvers/dr_numpy.py
compas_dr-0.3.1.dist-info/LICENSE
compas_dr-0.3.1.dist-info/METADATA
compas_dr-0.3.1.dist-info/WHEEL
compas_dr-0.3.1.dist-info/top_level.txt
compas_dr-0.3.1.dist-info/RECORD
